chart_beautifier/__init__.py
chart_beautifier/client.py
chart_beautifier/exceptions.py
chart_beautifier-0.1.3.dist-info/licenses/LICENSE
chart_beautifier-0.1.3.dist-info/METADATA
chart_beautifier-0.1.3.dist-info/WHEEL
chart_beautifier-0.1.3.dist-info/top_level.txt
chart_beautifier-0.1.3.dist-info/RECORD
