Metadata-Version: 2.4
Name: chart-beautifier
Version: 0.1.3
Summary: A Python SDK for creating beautiful and interactive charts
Home-page: https://github.com/yourusername/chart-beautifier
Author: Your Name
Author-email: Kostas Krachtopoulos <kkrachtop@gmail.com>
License-Expression: MIT
Project-URL: Homepage, https://github.com/yourusername/chart-beautifier
Project-URL: Documentation, https://chart-beautifier.readthedocs.io
Project-URL: Repository, https://github.com/yourusername/chart-beautifier
Project-URL: Issues, https://github.com/yourusername/chart-beautifier/issues
Keywords: charts,visualization,sdk,api
Classifier: Development Status :: 3 - Alpha
Classifier: Intended Audience :: Developers
Classifier: Programming Language :: Python :: 3
Classifier: Programming Language :: Python :: 3.8
Classifier: Programming Language :: Python :: 3.9
Classifier: Programming Language :: Python :: 3.10
Classifier: Programming Language :: Python :: 3.11
Classifier: Programming Language :: Python :: 3.12
Classifier: Programming Language :: Python :: 3.13
Requires-Python: >=3.8
License-File: LICENSE
Requires-Dist: requests>=2.25.0
Requires-Dist: pydantic>=1.8.0
Provides-Extra: dev
Requires-Dist: pytest>=6.0; extra == "dev"
Requires-Dist: pytest-cov>=2.0; extra == "dev"
Requires-Dist: black>=21.0; extra == "dev"
Requires-Dist: flake8>=3.8; extra == "dev"
Requires-Dist: mypy>=0.800; extra == "dev"
Dynamic: author
Dynamic: home-page
Dynamic: license-file
Dynamic: requires-python
